async_adbutils/__init__.py
async_adbutils/__main__.py
async_adbutils/_adb.py
async_adbutils/_device.py
async_adbutils/_proto.py
async_adbutils/_utils.py
async_adbutils/_version.py
async_adbutils/errors.py
async_adbutils/pidcat.py
async_adbutils-0.1.1.dist-info/licenses/AUTHORS
async_adbutils-0.1.1.dist-info/licenses/LICENSE
async_adbutils-0.1.1.dist-info/METADATA
async_adbutils-0.1.1.dist-info/WHEEL
async_adbutils-0.1.1.dist-info/top_level.txt
async_adbutils-0.1.1.dist-info/RECORD
