Metadata-Version: 2.4
Name: async_adbutils
Version: 0.1.1
Summary: Python adb async library for adb service. Fork maintained by DroidRun.
Author-email: tomin <tomin@tomin.com>, shahir <shahir@droidrun.ai>
License-Expression: MIT
Project-URL: homepage, https://github.com/droidrun/async_adbutils
Project-URL: repository, https://github.com/droidrun/async_adbutils
Project-URL: documentation, https://github.com/droidrun/async_adbutils
Keywords: adb,adbutils,async,android,droidrun
Classifier: Operating System :: OS Independent
Classifier: Programming Language :: Python :: 3
Classifier: Programming Language :: Python :: 3.10
Classifier: Programming Language :: Python :: 3.11
Classifier: Programming Language :: Python :: 3.12
Classifier: Programming Language :: Python :: 3.13
Requires-Python: >=3.10
License-File: LICENSE
License-File: AUTHORS
Requires-Dist: httpx
Requires-Dist: Pillow
Requires-Dist: retry
Requires-Dist: apkutils2
Dynamic: license-file
